<?xml version="1.0"?>
<tfs_active_incidents>
  <update_from_db_time>2021-04-06 15:30:02</update_from_db_time>
  <event>
    <prime_street>M8V</prime_street>
    <cross_streets/>
    <dispatch_time>2021-04-06 13:07:01</dispatch_time>
    <event_num>F21031008</event_num>
    <event_type>MEDICAL</event_type>
    <alarm_lev>0</alarm_lev>
    <beat>433</beat>
    <units_disp> A433</units_disp>
  </event>
  <event>
    <prime_street>M2J</prime_street>
    <cross_streets/>
    <dispatch_time>2021-04-06 15:18:45</dispatch_time>
    <event_num>F21031064</event_num>
    <event_type>MEDICAL</event_type>
    <alarm_lev>0</alarm_lev>
    <beat>115</beat>
    <units_disp> R115</units_disp>
  </event>
  <event>
    <prime_street>MILL RD, ET</prime_street>
    <cross_streets>BURNHAMTHORPE RD / REDSTONE PATH</cross_streets>
    <dispatch_time>2021-04-06 15:24:43</dispatch_time>
    <event_num>F21031065</event_num>
    <event_type>Rescue - Elevator</event_type>
    <alarm_lev>0</alarm_lev>
    <beat>444</beat>
    <units_disp> S445, R444</units_disp>
  </event>
  <event>
    <prime_street>M4B</prime_street>
    <cross_streets/>
    <dispatch_time>2021-04-06 15:26:39</dispatch_time>
    <event_num>F21031066</event_num>
    <event_type>MEDICAL</event_type>
    <alarm_lev>0</alarm_lev>
    <beat>224</beat>
    <units_disp> R224</units_disp>
  </event>
</tfs_active_incidents>
