<?xml version="1.0"?>
<tfs_active_incidents>
  <update_from_db_time>2020-10-24 07:40:02</update_from_db_time>
  <event>
    <prime_street>NAVY WHARF CRT, TT</prime_street>
    <cross_streets>BREMNER BLVD / BLUE JAYS WAY</cross_streets>
    <dispatch_time>2020-10-24 07:16:44</dispatch_time>
    <event_num>F20106090</event_num>
    <event_type>Vehicle Accident - Trapped</event_type>
    <alarm_lev>0</alarm_lev>
    <beat>334</beat>
    <units_disp> P315, C33, P334, S331</units_disp>
  </event>
</tfs_active_incidents>
