<?xml version="1.0"?>
<tfs_active_incidents>
  <update_from_db_time>2021-03-25 15:15:02</update_from_db_time>
  <event>
    <prime_street> </prime_street>
    <cross_streets> / </cross_streets>
    <dispatch_time>2021-03-25 13:49:13</dispatch_time>
    <event_num>F21026717</event_num>
    <event_type>Fire - Encampment</event_type>
    <alarm_lev>0</alarm_lev>
    <beat>146</beat>
    <units_disp> A142, C41</units_disp>
  </event>
  <event>
    <prime_street>FINCH AVE, NY</prime_street>
    <cross_streets>HUMBER RIVER RECREATIONAL TRL / ISLINGTON AVE</cross_streets>
    <dispatch_time>2021-03-25 14:48:45</dispatch_time>
    <event_num>F21026741</event_num>
    <event_type>Alarm Commercial/Industrial</event_type>
    <alarm_lev>0</alarm_lev>
    <beat>411</beat>
    <units_disp> R411, R413, A411, C41, P415</units_disp>
  </event>
  <event>
    <prime_street>PANORAMA CRT, ET</prime_street>
    <cross_streets>KIPLING AVE / </cross_streets>
    <dispatch_time>2021-03-25 15:03:28</dispatch_time>
    <event_num>F21026743</event_num>
    <event_type>Fire -  Highrise Residential</event_type>
    <alarm_lev>0</alarm_lev>
    <beat>413</beat>
    <units_disp> P415, R411, A411, C41, R412, R441</units_disp>
  </event>
</tfs_active_incidents>
