<?xml version="1.0"?>
<tfs_active_incidents>
  <update_from_db_time>2020-12-05 05:20:02</update_from_db_time>
  <event>
    <prime_street>EATON PARK LANE, SC</prime_street>
    <cross_streets>BRIDLETOWNE CRCL / BRIDLETOWNE CRCL</cross_streets>
    <dispatch_time>2020-12-05 03:55:38</dispatch_time>
    <event_num>F20120904</event_num>
    <event_type>Vehicle Fire - Underground</event_type>
    <alarm_lev>0</alarm_lev>
    <beat>244</beat>
    <units_disp> C23, P245, R243, S232, A113, HR114, P116, R115, C24, P242, P244, R241, A244, A244, MPV341, A341, R243, LA231, A213</units_disp>
  </event>
  <event>
    <prime_street>LAWRENCE AVE, NY</prime_street>
    <cross_streets>DUFFERIN ST / GOOD SHEPHERD CRT</cross_streets>
    <dispatch_time>2020-12-05 04:51:25</dispatch_time>
    <event_num>F20120913</event_num>
    <event_type>Check Call</event_type>
    <alarm_lev>0</alarm_lev>
    <beat>145</beat>
    <units_disp> P132</units_disp>
  </event>
  <event>
    <prime_street> </prime_street>
    <cross_streets> / </cross_streets>
    <dispatch_time>2020-12-05 04:59:55</dispatch_time>
    <event_num>F20120915</event_num>
    <event_type>Hazmat Level 1</event_type>
    <alarm_lev>0</alarm_lev>
    <beat>322</beat>
    <units_disp> R224</units_disp>
  </event>
  <event>
    <prime_street>M1M</prime_street>
    <cross_streets/>
    <dispatch_time>2020-12-05 05:08:42</dispatch_time>
    <event_num>F20120916</event_num>
    <event_type>MEDICAL</event_type>
    <alarm_lev>0</alarm_lev>
    <beat>223</beat>
    <units_disp> P223</units_disp>
  </event>
  <event>
    <prime_street>M4K</prime_street>
    <cross_streets/>
    <dispatch_time>2020-12-05 05:12:49</dispatch_time>
    <event_num>F20120917</event_num>
    <event_type>MEDICAL</event_type>
    <alarm_lev>0</alarm_lev>
    <beat>322</beat>
    <units_disp> A322</units_disp>
  </event>
</tfs_active_incidents>
