<?xml version="1.0"?>
<tfs_active_incidents>
  <update_from_db_time>2020-11-26 14:20:05</update_from_db_time>
  <event>
    <prime_street>SPADINA AVE, TT</prime_street>
    <cross_streets>DUNDAS ST W / GLEN BAILLIE PL</cross_streets>
    <dispatch_time>2020-11-26 13:59:34</dispatch_time>
    <event_num>F20117958</event_num>
    <event_type>Alarm Commercial/Industrial</event_type>
    <alarm_lev>0</alarm_lev>
    <beat>315</beat>
    <units_disp> P332, P314, A312, C33, P312, A331, P315</units_disp>
  </event>
  <event>
    <prime_street>JANE ST, NY</prime_street>
    <cross_streets>QUEEN'S DR / KING ST</cross_streets>
    <dispatch_time>2020-11-26 14:08:22</dispatch_time>
    <event_num>F20117960</event_num>
    <event_type>Alarm Highrise Residential</event_type>
    <alarm_lev>0</alarm_lev>
    <beat>442</beat>
    <units_disp> R421, P422, A133, C14, P145, C41</units_disp>
  </event>
  <event>
    <prime_street>VICKSON CRT, ET</prime_street>
    <cross_streets>THE EAST MALL / TREMONT RD</cross_streets>
    <dispatch_time>2020-11-26 14:13:11</dispatch_time>
    <event_num>F20117961</event_num>
    <event_type>Alarm Residential</event_type>
    <alarm_lev>0</alarm_lev>
    <beat>432</beat>
    <units_disp> P445, R444, C44, P431, PL432</units_disp>
  </event>
  <event>
    <prime_street>M5B</prime_street>
    <cross_streets/>
    <dispatch_time>2020-11-26 14:15:18</dispatch_time>
    <event_num>F20117962</event_num>
    <event_type>MEDICAL</event_type>
    <alarm_lev>0</alarm_lev>
    <beat>314</beat>
    <units_disp> R325</units_disp>
  </event>
</tfs_active_incidents>
