<?xml version="1.0"?>
<tfs_active_incidents>
  <update_from_db_time>2021-03-23 07:40:02</update_from_db_time>
  <event>
    <prime_street>HORSHAM AVE, NY</prime_street>
    <cross_streets>STAFFORD RD / BATHURST ST</cross_streets>
    <dispatch_time>2021-03-23 01:46:26</dispatch_time>
    <event_num>F21025815</event_num>
    <event_type>Fire - Residential</event_type>
    <alarm_lev>0</alarm_lev>
    <beat>112</beat>
    <units_disp> S143, R112, P114, P143, C14, T114, LA111, P141, P132, P121, P111, P114</units_disp>
  </event>
  <event>
    <prime_street>DUFFERIN ST, TT</prime_street>
    <cross_streets>DUFFERIN GROVE PARK TRL / DUFFERIN GROVE PARK TRL</cross_streets>
    <dispatch_time>2021-03-23 07:25:56</dispatch_time>
    <event_num>F21025861</event_num>
    <event_type>Alarm Commercial/Industrial</event_type>
    <alarm_lev>0</alarm_lev>
    <beat>345</beat>
    <units_disp> P331, R345, A345, R426, C34</units_disp>
  </event>
  <event>
    <prime_street>M6N</prime_street>
    <cross_streets/>
    <dispatch_time>2021-03-23 07:30:44</dispatch_time>
    <event_num>F21025862</event_num>
    <event_type>MEDICAL</event_type>
    <alarm_lev>0</alarm_lev>
    <beat>342</beat>
    <units_disp> P342</units_disp>
  </event>
</tfs_active_incidents>
