<?xml version="1.0"?>
<tfs_active_incidents>
  <update_from_db_time>2020-12-20 14:30:02</update_from_db_time>
  <event>
    <prime_street>M5T</prime_street>
    <cross_streets/>
    <dispatch_time>2020-12-20 14:11:10</dispatch_time>
    <event_num>F20126220</event_num>
    <event_type>MEDICAL</event_type>
    <alarm_lev>0</alarm_lev>
    <beat>315</beat>
    <units_disp> P315</units_disp>
  </event>
  <event>
    <prime_street>M6M</prime_street>
    <cross_streets/>
    <dispatch_time>2020-12-20 14:17:43</dispatch_time>
    <event_num>F20126221</event_num>
    <event_type>MEDICAL</event_type>
    <alarm_lev>0</alarm_lev>
    <beat>421</beat>
    <units_disp> R423</units_disp>
  </event>
  <event>
    <prime_street> </prime_street>
    <cross_streets>HIGHWAY 27 N / HUMBER COLLEGE BLVD</cross_streets>
    <dispatch_time>2020-12-20 14:23:37</dispatch_time>
    <event_num>F20126222</event_num>
    <event_type>Vehicle Accident - Trapped</event_type>
    <alarm_lev>0</alarm_lev>
    <beat>413</beat>
    <units_disp> R413, C41, R412, S331</units_disp>
  </event>
  <event>
    <prime_street> </prime_street>
    <cross_streets>ST CLAIR AVE W / AVENUE RD</cross_streets>
    <dispatch_time>2020-12-20 14:26:22</dispatch_time>
    <event_num>F20126223</event_num>
    <event_type>Vehicle - Personal Injury</event_type>
    <alarm_lev>0</alarm_lev>
    <beat>311</beat>
    <units_disp> P311</units_disp>
  </event>
</tfs_active_incidents>
