<?xml version="1.0"?>
<tfs_active_incidents>
  <update_from_db_time>2021-01-10 11:10:02</update_from_db_time>
  <event>
    <prime_street>M5A</prime_street>
    <cross_streets/>
    <dispatch_time>2021-01-02 11:11:32</dispatch_time>
    <event_num>F21000460</event_num>
    <event_type>MEDICAL</event_type>
    <alarm_lev>0</alarm_lev>
    <beat>325</beat>
    <units_disp> R325, ZMPS1</units_disp>
  </event>
  <event>
    <prime_street>M4X</prime_street>
    <cross_streets/>
    <dispatch_time>2021-01-10 10:22:44</dispatch_time>
    <event_num>F21002887</event_num>
    <event_type>MEDICAL</event_type>
    <alarm_lev>0</alarm_lev>
    <beat>313</beat>
    <units_disp> P313</units_disp>
  </event>
  <event>
    <prime_street>M3M</prime_street>
    <cross_streets/>
    <dispatch_time>2021-01-10 10:53:33</dispatch_time>
    <event_num>F21002894</event_num>
    <event_type>MEDICAL</event_type>
    <alarm_lev>0</alarm_lev>
    <beat>146</beat>
    <units_disp> P146</units_disp>
  </event>
  <event>
    <prime_street>M1W</prime_street>
    <cross_streets/>
    <dispatch_time>2021-01-10 10:54:15</dispatch_time>
    <event_num>F21002895</event_num>
    <event_type>MEDICAL</event_type>
    <alarm_lev>0</alarm_lev>
    <beat>241</beat>
    <units_disp> R241</units_disp>
  </event>
  <event>
    <prime_street>M6C</prime_street>
    <cross_streets/>
    <dispatch_time>2021-01-10 10:54:43</dispatch_time>
    <event_num>F21002896</event_num>
    <event_type>MEDICAL</event_type>
    <alarm_lev>0</alarm_lev>
    <beat>343</beat>
    <units_disp> P343</units_disp>
  </event>
  <event>
    <prime_street>M2R</prime_street>
    <cross_streets/>
    <dispatch_time>2021-01-10 10:54:37</dispatch_time>
    <event_num>F21002897</event_num>
    <event_type>MEDICAL</event_type>
    <alarm_lev>0</alarm_lev>
    <beat>112</beat>
    <units_disp> R112</units_disp>
  </event>
  <event>
    <prime_street>M6M</prime_street>
    <cross_streets/>
    <dispatch_time>2021-01-10 11:00:01</dispatch_time>
    <event_num>F21002898</event_num>
    <event_type>MEDICAL</event_type>
    <alarm_lev>0</alarm_lev>
    <beat>133</beat>
    <units_disp> R133</units_disp>
  </event>
</tfs_active_incidents>
