<?xml version="1.0"?>
<tfs_active_incidents>
  <update_from_db_time>2020-10-21 09:30:02</update_from_db_time>
  <event>
    <prime_street>BURBANK DR, NY</prime_street>
    <cross_streets>BURLEIGH HEIGHTS DR / CANARY CRES</cross_streets>
    <dispatch_time>2020-10-21 08:43:22</dispatch_time>
    <event_num>F20104982</event_num>
    <event_type>Public Hazard</event_type>
    <alarm_lev>0</alarm_lev>
    <beat>111</beat>
    <units_disp> P111</units_disp>
  </event>
  <event>
    <prime_street>SHERBOURNE ST, TT</prime_street>
    <cross_streets>WELLESLEY ST E / LOURDES LANE</cross_streets>
    <dispatch_time>2020-10-21 09:00:55</dispatch_time>
    <event_num>F20104988</event_num>
    <event_type>Fire -  Highrise Residential</event_type>
    <alarm_lev>1</alarm_lev>
    <beat>313</beat>
    <units_disp> A312, C31, P312, P313, R325, S313, A325, LA333, R345, R134</units_disp>
  </event>
  <event>
    <prime_street>TEMAGAMI CRT, NY</prime_street>
    <cross_streets>ABITIBI AVE / </cross_streets>
    <dispatch_time>2020-10-21 09:09:54</dispatch_time>
    <event_num>F20104992</event_num>
    <event_type>Fire - Residential</event_type>
    <alarm_lev>1</alarm_lev>
    <beat>111</beat>
    <units_disp> P116, P143, P123, S232, A244, C22, LA111, R115, T114, R224</units_disp>
  </event>
  <event>
    <prime_street>DAVENPORT RD, TT</prime_street>
    <cross_streets>BEDFORD RD / DUPONT ST</cross_streets>
    <dispatch_time>2020-10-21 09:17:26</dispatch_time>
    <event_num>F20104993</event_num>
    <event_type>Alarm Commercial/Industrial</event_type>
    <alarm_lev>0</alarm_lev>
    <beat>344</beat>
    <units_disp> P311, R345, A315, C33, P343</units_disp>
  </event>
  <event>
    <prime_street>M9M</prime_street>
    <cross_streets/>
    <dispatch_time>2020-10-21 09:18:22</dispatch_time>
    <event_num>F20104994</event_num>
    <event_type>MEDICAL</event_type>
    <alarm_lev>0</alarm_lev>
    <beat>411</beat>
    <units_disp> A411</units_disp>
  </event>
  <event>
    <prime_street>M1P</prime_street>
    <cross_streets/>
    <dispatch_time>2020-10-21 09:24:00</dispatch_time>
    <event_num>F20104995</event_num>
    <event_type>MEDICAL</event_type>
    <alarm_lev>0</alarm_lev>
    <beat>243</beat>
    <units_disp> R243</units_disp>
  </event>
</tfs_active_incidents>
