<?xml version="1.0"?>
<tfs_active_incidents>
  <update_from_db_time>2020-11-01 10:20:02</update_from_db_time>
  <event>
    <prime_street>M8Z</prime_street>
    <cross_streets/>
    <dispatch_time>2020-11-01 09:39:06</dispatch_time>
    <event_num>F20108958</event_num>
    <event_type>MEDICAL</event_type>
    <alarm_lev>0</alarm_lev>
    <beat>433</beat>
    <units_disp> P433</units_disp>
  </event>
  <event>
    <prime_street> </prime_street>
    <cross_streets>WINDERMERE AVE / LAKE SHORE BLVD W</cross_streets>
    <dispatch_time>2020-11-01 09:56:18</dispatch_time>
    <event_num>F20108963</event_num>
    <event_type>Check Call</event_type>
    <alarm_lev>0</alarm_lev>
    <beat>425</beat>
    <units_disp> R425</units_disp>
  </event>
  <event>
    <prime_street>M6G</prime_street>
    <cross_streets/>
    <dispatch_time>2020-11-01 10:12:24</dispatch_time>
    <event_num>F20108966</event_num>
    <event_type>MEDICAL</event_type>
    <alarm_lev>0</alarm_lev>
    <beat>343</beat>
    <units_disp> P343</units_disp>
  </event>
  <event>
    <prime_street>M5A</prime_street>
    <cross_streets/>
    <dispatch_time>2020-11-01 10:13:05</dispatch_time>
    <event_num>F20108967</event_num>
    <event_type>MEDICAL</event_type>
    <alarm_lev>0</alarm_lev>
    <beat>325</beat>
    <units_disp> R325</units_disp>
  </event>
  <event>
    <prime_street>M5A</prime_street>
    <cross_streets/>
    <dispatch_time>2020-11-01 10:15:24</dispatch_time>
    <event_num>F20108968</event_num>
    <event_type>MEDICAL</event_type>
    <alarm_lev>0</alarm_lev>
    <beat>325</beat>
    <units_disp> A325</units_disp>
  </event>
</tfs_active_incidents>
