<tfs_active_incidents><update_from_db_time>2020-10-31 13:40:02</update_from_db_time><event><prime_street>COLEMAN AVE, TT</prime_street><cross_streets>COLEMAN PARK TRL / COLEMAN PARK TRL</cross_streets><dispatch_time>2020-10-30 20:08:38</dispatch_time><event_num>F20108346</event_num><event_type>Fire - Residential</event_type><alarm_lev>1</alarm_lev><beat>226</beat><units_disp> A222, P226, P227, R224, R225, C32, R235, A322, LA333, S313, C20, P323, R235, P233, P227, P226, FI8, C22, FI19</units_disp></event><event><prime_street>&#x20;</prime_street><cross_streets> / </cross_streets><dispatch_time>2020-10-31 12:37:34</dispatch_time><event_num>F20108580</event_num><event_type>Vehicle - Personal Injury Highway</event_type><alarm_lev>0</alarm_lev><beat>123</beat><units_disp> P123, P233</units_disp></event><event><prime_street>M1G</prime_street><cross_streets/><dispatch_time>2020-10-31 13:22:26</dispatch_time><event_num>F20108593</event_num><event_type>MEDICAL</event_type><alarm_lev>0</alarm_lev><beat>231</beat><units_disp> A231</units_disp></event><event><prime_street>M4C</prime_street><cross_streets/><dispatch_time>2020-10-31 13:27:15</dispatch_time><event_num>F20108594</event_num><event_type>MEDICAL</event_type><alarm_lev>0</alarm_lev><beat>226</beat><units_disp> P226</units_disp></event><event><prime_street>M1N</prime_street><cross_streets/><dispatch_time>2020-10-31 13:29:39</dispatch_time><event_num>F20108596</event_num><event_type>MEDICAL</event_type><alarm_lev>0</alarm_lev><beat>226</beat><units_disp> P227</units_disp></event><event><prime_street>M1X</prime_street><cross_streets/><dispatch_time>2020-10-31 13:30:26</dispatch_time><event_num>F20108597</event_num><event_type>MEDICAL</event_type><alarm_lev>0</alarm_lev><beat>211</beat><units_disp> P211</units_disp></event><event><prime_street>ST CLAIR AVE, TT</prime_street><cross_streets>HARVIE AVE / LANSDOWNE AVE</cross_streets><dispatch_time>2020-10-31 13:35:04</dispatch_time><event_num>F20108598</event_num><event_type>Vehicle Accident - Minor Fuel Leak</event_type><alarm_lev>0</alarm_lev><beat>342</beat><units_disp> P342</units_disp></event><event><prime_street>&#x20;</prime_street><cross_streets> / </cross_streets><dispatch_time>2020-10-31 13:36:25</dispatch_time><event_num>F20108599</event_num><event_type>Vehicle Fire - Highway</event_type><alarm_lev>0</alarm_lev><beat>123</beat><units_disp> P233, P245, C11</units_disp></event></tfs_active_incidents>
