<tfs_active_incidents><update_from_db_time>2020-10-31 16:45:02</update_from_db_time><event><prime_street>COLEMAN AVE, TT</prime_street><cross_streets>COLEMAN PARK TRL / COLEMAN PARK TRL</cross_streets><dispatch_time>2020-10-30 20:08:38</dispatch_time><event_num>F20108346</event_num><event_type>Fire - Residential</event_type><alarm_lev>1</alarm_lev><beat>226</beat><units_disp> A222, P226, P227, R224, R225, C32, R235, A322, LA333, S313, C20, P323, R235, P233, P227, P226, FI8, C22, FI19</units_disp></event><event><prime_street>LA ROSE AVE, ET</prime_street><cross_streets>SCARLETT RD / ARCADE DR</cross_streets><dispatch_time>2020-10-31 15:22:58</dispatch_time><event_num>F20108646</event_num><event_type>Fire -  Highrise Residential</event_type><alarm_lev>2</alarm_lev><beat>443</beat><units_disp> A421, C41, P422, P431, P442, R421, A433, LA421, R444, C44, P445, R425, S445, HR332, HZ145, R133, C40, P443, CMD30, C42, CMD30C</units_disp></event><event><prime_street>&#x20;</prime_street><cross_streets> / </cross_streets><dispatch_time>2020-10-31 15:39:54</dispatch_time><event_num>F20108654</event_num><event_type>Vehicle - Personal Injury Highway</event_type><alarm_lev>0</alarm_lev><beat>132</beat><units_disp> P131, P132</units_disp></event><event><prime_street>UNDERHILL DR, NY</prime_street><cross_streets>BROADLANDS BLVD / DOONAREE DR</cross_streets><dispatch_time>2020-10-31 15:40:44</dispatch_time><event_num>F20108656</event_num><event_type>Fire - Residential</event_type><alarm_lev>0</alarm_lev><beat>233</beat><units_disp> R235, P233, A222, C22, P245, P123, LA231</units_disp></event><event><prime_street>M2J</prime_street><cross_streets/><dispatch_time>2020-10-31 16:11:46</dispatch_time><event_num>F20108666</event_num><event_type>MEDICAL</event_type><alarm_lev>0</alarm_lev><beat>115</beat><units_disp> R115</units_disp></event><event><prime_street>&#x20;</prime_street><cross_streets>MARTIN GROVE RD / EGLINTON AVE W</cross_streets><dispatch_time>2020-10-31 16:13:13</dispatch_time><event_num>F20108667</event_num><event_type>Vehicle Accident - Trapped</event_type><alarm_lev>0</alarm_lev><beat>443</beat><units_disp> R441, A423, R411, S143, C14</units_disp></event><event><prime_street>WILLOWMOUNT DR, SC</prime_street><cross_streets>CHESTNUT CRES / ANACONDA AVE</cross_streets><dispatch_time>2020-10-31 16:35:15</dispatch_time><event_num>F20108673</event_num><event_type>Vehicle - Personal Injury</event_type><alarm_lev>0</alarm_lev><beat>222</beat><units_disp> P221</units_disp></event><event><prime_street>DUNDAS SQ, TT</prime_street><cross_streets>O'KEEFE LANE / VICTORIA ST</cross_streets><dispatch_time>2020-10-31 16:37:53</dispatch_time><event_num>F20108676</event_num><event_type>Alarm Highrise Residential</event_type><alarm_lev>0</alarm_lev><beat>314</beat><units_disp> P314, P332, A325, C33, R325</units_disp></event></tfs_active_incidents>
