<tfs_active_incidents><update_from_db_time>2021-04-01 02:50:02</update_from_db_time><event><prime_street>M6C</prime_street><cross_streets/><dispatch_time>2021-04-01 02:35:35</dispatch_time><event_num>F21029112</event_num><event_type>MEDICAL</event_type><alarm_lev>0</alarm_lev><beat>341</beat><units_disp> R341</units_disp></event><event><prime_street>DUGGAN AVE, TT</prime_street><cross_streets>LAWTON BLVD / ORIOLE PKWY</cross_streets><dispatch_time>2021-04-01 02:37:15</dispatch_time><event_num>F21029113</event_num><event_type>Alarm Residential</event_type><alarm_lev>0</alarm_lev><beat>311</beat><units_disp> P311, C31, A135, P135, R134</units_disp></event></tfs_active_incidents>
