<tfs_active_incidents><update_from_db_time>2020-12-03 08:20:03</update_from_db_time><event><prime_street>M4V</prime_street><cross_streets/><dispatch_time>2020-12-03 07:55:14</dispatch_time><event_num>F20120244</event_num><event_type>MEDICAL</event_type><alarm_lev>0</alarm_lev><beat>344</beat><units_disp> P312</units_disp></event><event><prime_street>M4Y</prime_street><cross_streets/><dispatch_time>2020-12-03 08:13:15</dispatch_time><event_num>F20120245</event_num><event_type>MEDICAL</event_type><alarm_lev>0</alarm_lev><beat>314</beat><units_disp> P314</units_disp></event></tfs_active_incidents>
