<tfs_active_incidents><update_from_db_time>2021-01-18 14:35:02</update_from_db_time><event><prime_street>CALLENDER ST, TT</prime_street><cross_streets>LN N QUEEN E TRILLER / HARVARD AVE</cross_streets><dispatch_time>2021-01-17 06:32:30</dispatch_time><event_num>F21004953</event_num><event_type>Fire - Residential</event_type><alarm_lev>2</alarm_lev><beat>426</beat><units_disp> R426, A426, C42, P426, P331, P344, LA421, R423, A331, S331, C34, R425, C33, HZ326, P315, R345, C40, CMD30, CMD30C, C42, FI19, R411, P426, A421, P432, P445, R444, P431, R413, P422, P426, R426, FI16</units_disp></event><event><prime_street>BERKELEY ST, TT</prime_street><cross_streets>SHUTER ST / COATSWORTH ST</cross_streets><dispatch_time>2021-01-18 05:18:40</dispatch_time><event_num>F21005187</event_num><event_type>Fire - Residential</event_type><alarm_lev>1</alarm_lev><beat>325</beat><units_disp> R325, P333, A325, C33, P313, P314, C33, LA333, P312, S313, T333, C30, C31, T333, P325, FI5, FI20, C30, P324</units_disp></event><event><prime_street>TRETHEWEY DR, YK</prime_street><cross_streets>CLEARVIEW HTS / KING GEORGE'S DR</cross_streets><dispatch_time>2021-01-18 14:19:19</dispatch_time><event_num>F21005317</event_num><event_type>Vehicle - Personal Injury</event_type><alarm_lev>0</alarm_lev><beat>133</beat><units_disp> R133</units_disp></event><event><prime_street>EVANSTON DR, NY</prime_street><cross_streets>BARKSDALE AVE / PURDON DR</cross_streets><dispatch_time>2021-01-18 14:20:15</dispatch_time><event_num>F21005318</event_num><event_type>Alarm Residential</event_type><alarm_lev>0</alarm_lev><beat>143</beat><units_disp> C14, P141, P143, R112, T114</units_disp></event><event><prime_street>M9N</prime_street><cross_streets/><dispatch_time>2021-01-18 14:20:47</dispatch_time><event_num>F21005319</event_num><event_type>MEDICAL</event_type><alarm_lev>0</alarm_lev><beat>442</beat><units_disp> P442</units_disp></event><event><prime_street>GRAYDON HALL DR, NY</prime_street><cross_streets>GRAYDON HALL PL / GRAYDON HALL PARK TRL</cross_streets><dispatch_time>2021-01-18 14:23:50</dispatch_time><event_num>F21005320</event_num><event_type>Alarm Highrise Residential</event_type><alarm_lev>0</alarm_lev><beat>115</beat><units_disp> R115, P123, A113, C11, P116</units_disp></event><event><prime_street>M5A</prime_street><cross_streets/><dispatch_time>2021-01-18 14:25:03</dispatch_time><event_num>F21005321</event_num><event_type>MEDICAL</event_type><alarm_lev>0</alarm_lev><beat>333</beat><units_disp> P333</units_disp></event><event><prime_street>M2R</prime_street><cross_streets/><dispatch_time>2021-01-18 14:25:03</dispatch_time><event_num>F21005322</event_num><event_type>MEDICAL</event_type><alarm_lev>0</alarm_lev><beat>112</beat><units_disp> P114</units_disp></event><event><prime_street>M4S</prime_street><cross_streets/><dispatch_time>2021-01-18 14:29:36</dispatch_time><event_num>F21005323</event_num><event_type>MEDICAL</event_type><alarm_lev>0</alarm_lev><beat>134</beat><units_disp> R134</units_disp></event><event><prime_street>M5A</prime_street><cross_streets/><dispatch_time>2021-01-18 14:31:48</dispatch_time><event_num>F21005324</event_num><event_type>MEDICAL</event_type><alarm_lev>0</alarm_lev><beat>325</beat><units_disp> P325</units_disp></event></tfs_active_incidents>
