<tfs_active_incidents><update_from_db_time>2021-02-05 01:20:02</update_from_db_time><event><prime_street>FRONT ST, TT</prime_street><cross_streets>SIMCOE ST / JOHN ST</cross_streets><dispatch_time>2021-02-05 01:01:45</dispatch_time><event_num>F21010728</event_num><event_type>Alarm Highrise - Commercial - Downtown</event_type><alarm_lev>0</alarm_lev><beat>332</beat><units_disp> P332, P334, C33, HR332, P333, T333</units_disp></event><event><prime_street>M5R</prime_street><cross_streets/><dispatch_time>2021-02-05 01:07:16</dispatch_time><event_num>F21010729</event_num><event_type>MEDICAL</event_type><alarm_lev>0</alarm_lev><beat>344</beat><units_disp> P312</units_disp></event><event><prime_street>M2M</prime_street><cross_streets/><dispatch_time>2021-02-05 01:14:05</dispatch_time><event_num>F21010730</event_num><event_type>MEDICAL</event_type><alarm_lev>0</alarm_lev><beat>114</beat><units_disp> P114</units_disp></event><event><prime_street>M8V</prime_street><cross_streets/><dispatch_time>2021-02-05 01:14:50</dispatch_time><event_num>F21010731</event_num><event_type>MEDICAL</event_type><alarm_lev>0</alarm_lev><beat>435</beat><units_disp> R435</units_disp></event><event><prime_street>M2R</prime_street><cross_streets/><dispatch_time>2021-02-05 01:15:58</dispatch_time><event_num>F21010732</event_num><event_type>MEDICAL</event_type><alarm_lev>0</alarm_lev><beat>112</beat><units_disp> R112</units_disp></event></tfs_active_incidents>
