<tfs_active_incidents><update_from_db_time>2020-12-20 10:55:02</update_from_db_time><event><prime_street>M6R</prime_street><cross_streets/><dispatch_time>2020-12-20 09:44:54</dispatch_time><event_num>F20126149</event_num><event_type>MEDICAL</event_type><alarm_lev>0</alarm_lev><beat>426</beat><units_disp> R426</units_disp></event><event><prime_street>SORAUREN AVE, TT</prime_street><cross_streets>LN N QUEEN E SORAUREN / SAUNDERS AVE</cross_streets><dispatch_time>2020-12-20 10:17:51</dispatch_time><event_num>F20126155</event_num><event_type>Fire - Other</event_type><alarm_lev>0</alarm_lev><beat>426</beat><units_disp> P426, A426, C34, P331</units_disp></event><event><prime_street>M4S</prime_street><cross_streets/><dispatch_time>2020-12-20 10:17:52</dispatch_time><event_num>F20126156</event_num><event_type>MEDICAL</event_type><alarm_lev>0</alarm_lev><beat>134</beat><units_disp> R134</units_disp></event><event><prime_street>NORDIN AVE, ET</prime_street><cross_streets>WARNICA AVE / WOOLGAR AVE</cross_streets><dispatch_time>2020-12-20 10:23:08</dispatch_time><event_num>F20126160</event_num><event_type>Fire - Residential</event_type><alarm_lev>0</alarm_lev><beat>433</beat><units_disp> P431, P433, R434, R435, A433, C43</units_disp></event><event><prime_street>NEPTUNE DR, NY</prime_street><cross_streets>RAJAH ST / AMEER AVE</cross_streets><dispatch_time>2020-12-20 10:31:18</dispatch_time><event_num>F20126164</event_num><event_type>Alarm Residential</event_type><alarm_lev>0</alarm_lev><beat>132</beat><units_disp> A135, C13, P121, P131, P132</units_disp></event><event><prime_street>M6G</prime_street><cross_streets/><dispatch_time>2020-12-20 10:31:46</dispatch_time><event_num>F20126165</event_num><event_type>MEDICAL</event_type><alarm_lev>0</alarm_lev><beat>343</beat><units_disp> P343</units_disp></event><event><prime_street>M9V</prime_street><cross_streets/><dispatch_time>2020-12-20 10:49:19</dispatch_time><event_num>F20126167</event_num><event_type>MEDICAL</event_type><alarm_lev>0</alarm_lev><beat>413</beat><units_disp> A411</units_disp></event></tfs_active_incidents>
