<tfs_active_incidents><update_from_db_time>2021-01-27 10:20:02</update_from_db_time><event><prime_street>&#x20;</prime_street><cross_streets>EGLINTON AVE W / AVENUE RD</cross_streets><dispatch_time>2021-01-27 09:07:49</dispatch_time><event_num>F21007917</event_num><event_type>Vehicle - Personal Injury</event_type><alarm_lev>0</alarm_lev><beat>135</beat><units_disp> P135, P135</units_disp></event><event><prime_street>HILLSDALE AVE, TT</prime_street><cross_streets>REDPATH AVE / MOUNT PLEASANT RD</cross_streets><dispatch_time>2021-01-27 09:48:53</dispatch_time><event_num>F21007927</event_num><event_type>Natural Gas Leak</event_type><alarm_lev>0</alarm_lev><beat>134</beat><units_disp> P324, C13, R134, HZ326, C13</units_disp></event><event><prime_street>M8Y</prime_street><cross_streets/><dispatch_time>2021-01-27 10:05:47</dispatch_time><event_num>F21007930</event_num><event_type>MEDICAL</event_type><alarm_lev>0</alarm_lev><beat>433</beat><units_disp> P433</units_disp></event><event><prime_street>RAITHERM RD, NY</prime_street><cross_streets>GURNEY CRES / GURNEY CRES</cross_streets><dispatch_time>2021-01-27 10:07:14</dispatch_time><event_num>F21007931</event_num><event_type>Fire Alarm - Check Call</event_type><alarm_lev>0</alarm_lev><beat>133</beat><units_disp> R133, P132, A133, C13, P145</units_disp></event><event><prime_street>M8Z</prime_street><cross_streets/><dispatch_time>2021-01-27 10:12:27</dispatch_time><event_num>F21007932</event_num><event_type>MEDICAL</event_type><alarm_lev>0</alarm_lev><beat>433</beat><units_disp> R435</units_disp></event><event><prime_street>M9W</prime_street><cross_streets/><dispatch_time>2021-01-27 10:13:13</dispatch_time><event_num>F21007933</event_num><event_type>MEDICAL</event_type><alarm_lev>0</alarm_lev><beat>412</beat><units_disp> R412</units_disp></event></tfs_active_incidents>
