<tfs_active_incidents><update_from_db_time>2020-12-26 00:50:02</update_from_db_time><event><prime_street>WARDEN AVE, SC</prime_street><cross_streets>BOEM AVE / MANHATTAN DR</cross_streets><dispatch_time>2020-12-25 23:59:56</dispatch_time><event_num>F20128157</event_num><event_type>Vehicle - Personal Injury</event_type><alarm_lev>0</alarm_lev><beat>245</beat><units_disp> P245</units_disp></event><event><prime_street>M4S</prime_street><cross_streets/><dispatch_time>2020-12-26 00:31:51</dispatch_time><event_num>F20128164</event_num><event_type>MEDICAL</event_type><alarm_lev>0</alarm_lev><beat>311</beat><units_disp> P311</units_disp></event><event><prime_street>RUSHOLME RD, TT</prime_street><cross_streets>HEPBOURNE ST / BLOOR ST W</cross_streets><dispatch_time>2020-12-26 00:33:55</dispatch_time><event_num>F20128165</event_num><event_type>Alarm Highrise Residential</event_type><alarm_lev>0</alarm_lev><beat>345</beat><units_disp> R345, A345, C34, P315, R426</units_disp></event></tfs_active_incidents>
