<tfs_active_incidents><update_from_db_time>2021-02-16 19:55:02</update_from_db_time><event><prime_street>GOSFORD BLVD, NY</prime_street><cross_streets>ELM PARK TRL / BLACKSMITH CRES</cross_streets><dispatch_time>2021-02-16 19:27:17</dispatch_time><event_num>F21014603</event_num><event_type>Fire -  Highrise Residential</event_type><alarm_lev>0</alarm_lev><beat>142</beat><units_disp> A142, C14, P141, P146, R112, R411</units_disp></event><event><prime_street>ISLINGTON AVE, ET</prime_street><cross_streets>BROMLEY CRES / THORNCREST RD</cross_streets><dispatch_time>2021-02-16 19:39:02</dispatch_time><event_num>F21014604</event_num><event_type>Alarm Commercial/Industrial</event_type><alarm_lev>0</alarm_lev><beat>443</beat><units_disp> P443, P445, A421, C44, R444</units_disp></event><event><prime_street>BROADMEAD AVE, SC</prime_street><cross_streets>BROOKLAWN AVE / HAREWOOD AVE</cross_streets><dispatch_time>2021-02-16 19:43:08</dispatch_time><event_num>F21014605</event_num><event_type>Water Problem - Non Emergency</event_type><alarm_lev>0</alarm_lev><beat>223</beat><units_disp> A222, P223</units_disp></event><event><prime_street>GOLDFINCH CRT, NY</prime_street><cross_streets> / FINCH AVE W</cross_streets><dispatch_time>2021-02-16 19:48:07</dispatch_time><event_num>F21014606</event_num><event_type>Alarms Highrise Residential North</event_type><alarm_lev>0</alarm_lev><beat>112</beat><units_disp> P143, P114, C13, HR114, P111, T114</units_disp></event><event><prime_street>M6M</prime_street><cross_streets/><dispatch_time>2021-02-16 19:48:35</dispatch_time><event_num>F21014607</event_num><event_type>MEDICAL</event_type><alarm_lev>0</alarm_lev><beat>421</beat><units_disp> R421</units_disp></event></tfs_active_incidents>
