<tfs_active_incidents><update_from_db_time>2021-03-25 00:20:02</update_from_db_time><event><prime_street>FRIZZELL AVE, TT</prime_street><cross_streets>LN E PAPE S FRIZELL / </cross_streets><dispatch_time>2021-03-24 23:48:29</dispatch_time><event_num>F21026554</event_num><event_type>Natural Gas Leak</event_type><alarm_lev>0</alarm_lev><beat>324</beat><units_disp> P145, P324, C32, HZ326, A324</units_disp></event><event><prime_street>DANFORTH AVE, TT</prime_street><cross_streets>PLAYTER BLVD / BOWDEN ST</cross_streets><dispatch_time>2021-03-24 23:59:21</dispatch_time><event_num>F21026555</event_num><event_type>Fire - Grass/Rubbish</event_type><alarm_lev>0</alarm_lev><beat>313</beat><units_disp> P313</units_disp></event><event><prime_street>M2N</prime_street><cross_streets/><dispatch_time>2021-03-25 00:11:26</dispatch_time><event_num>F21026557</event_num><event_type>MEDICAL</event_type><alarm_lev>0</alarm_lev><beat>122</beat><units_disp> R122</units_disp></event><event><prime_street>ROSEMOUNT DR, SC</prime_street><cross_streets>HARDCASTLE ST / RANSTONE GDNS</cross_streets><dispatch_time>2021-03-25 00:16:01</dispatch_time><event_num>F21026558</event_num><event_type>Alarm Residential</event_type><alarm_lev>0</alarm_lev><beat>221</beat><units_disp> P221, A222, C22, P222, P245</units_disp></event></tfs_active_incidents>
